Workbook

Sheet Cash Flow Statement_Actual
A1: Line Item | B1: 44835 | C1: 44927 | D1: 45017 | E1: 45108 | F1: 45200 | G1: 45292 | H1: 45383 | I1: 45474 | J1: 45566 | K1: 45658 | L1: 45748 | M1: 45839 | N1: 45931 | O1: 46023 | P1: 46113 | Q1: 46204 | R1: 46296 | S1: 46388 | T1: 46478 | U1: 46569 | V1: 46661 | W1: 46753 | X1: 46844 | Y1: 46935 | Z1: 47027
A2: Opening Cash Balance | B2: 5297 | C2: =B33 -> 9007.354 | D2: =C33 -> 970.11401 | E2: =D33 -> 69128.379 | F2: =E33 -> 61973.067 | G2: =F33 -> 3377.1199 | H2: =G33 -> 3199.7225 | I2: =H33 -> 36410.411 | J2: =I33 -> 9217.393 | ... N2: =M33 -> 106260.37 | O2: 0 | P2: 0 | Q2: 0 | R2: 0 | S2: 0 | T2: 0 | U2: 0 | V2: 0 | W2: 0 | X2: 0 | Y2: 0 | Z2: 0
A3: Revenue (excl. VAT) | B3: =Sales_Actual!B36 -> 135435.69 | C3: =Sales_Actual!C36 -> 244562.5 | D3: =Sales_Actual!D36 -> 321836.12 | E3: =Sales_Actual!E36 -> 251700.58 | F3: =Sales_Actual!F36 -> 216272.4 | G3: =Sales_Actual!G36 -> 288852.45 | H3: =Sales_Actual!H36 -> 319230.2 | I3: =Sales_Actual!I36 -> 276102 | ... Z3: =Sales_Actual!Z36 -> 0
A4: COGS (excl.VAT) | B4: =COGS_Actual!B36 -> 89468.323 | C4: =COGS_Actual!C36 -> 168385.51 | D4: =COGS_Actual!D36 -> 211331 | E4: =COGS_Actual!E36 -> 160344.73 | F4: =COGS_Actual!F36 -> 144339.06 | G4: =COGS_Actual!G36 -> 191698.5 | H4: =COGS_Actual!H36 -> 211024.61 | I4: =COGS_Actual!I36 -> 189879.1 | ... Z4: =COGS_Actual!Z36 -> 0
A5: Gross Profit | B5: =B3-B4 -> 45967.363 | C5: =C3-C4 -> 76176.992 | D5: =D3-D4 -> 110505.11 | E5: =E3-E4 -> 91355.855 | F5: =F3-F4 -> 71933.345 | G5: =G3-G4 -> 97153.946 | H5: =H3-H4 -> 108205.59 | I5: =I3-I4 -> 86222.904 | ... Z5: =Z3-Z4 -> 0
A6: Other Operating Income | B6: 14399.516 | C6: 7124.7716 | D6: 7284.9605 | E6: 12710.128 | F6: 15390.559 | G6: 29039.315 | H6: 7776.3836 | I6: 13914.017 | J6: 48525.177 | K6: 19263.813 | L6: 13773.09 | M6: 11387.527 | N6: 14025.018 | O6: 0 | P6: 0 | Q6: 0 | R6: 0 | S6: 0 | T6: 0 | U6: 0 | V6: 0 | W6: 0 | X6: 0 | Y6: 0 | Z6: 0
A7: Administrative Expenses | B7: 5221.41 | C7: 5077.4039 | D7: 5292.0598 | E7: 5445.8854 | F7: 5947.9818 | G7: 6276.1936 | H7: 6158.1913 | I7: 6262.9148 | J7: 6849.6307 | K7: 6976.5649 | L7: 7389.3894 | M7: 7633.5355 | N7: 7850.9179 | O7: 0 | P7: 0 | Q7: 0 | R7: 0 | S7: 0 | T7: 0 | U7: 0 | V7: 0 | W7: 0 | X7: 0 | Y7: 0 | Z7: 0
A8: Selling Expenses | B8: 10791.768 | C8: 22118.186 | D8: 22270.877 | E8: 18925.54 | F8: 17371.466 | G8: 27549.329 | H8: 25308.563 | I8: 19790.537 | J8: 11919.094 | K8: 29448.341 | L8: 28097.445 | M8: 21039.853 | N8: 18429.032 | O8: 0 | P8: 0 | Q8: 0 | R8: 0 | S8: 0 | T8: 0 | U8: 0 | V8: 0 | W8: 0 | X8: 0 | Y8: 0 | Z8: 0
A9: Other Operating Expenses | B9: 13789 | C9: 9119.4 | D9: 5668 | E9: 6575 | F9: 20570 | G9: 39639 | H9: 10496.1 | I9: 19853 | J9: 22147.3 | K9: 26623.9 | L9: 18349 | M9: 8578 | N9: 11553 | O9: 0 | P9: 0 | Q9: 0 | R9: 0 | S9: 0 | T9: 0 | U9: 0 | V9: 0 | W9: 0 | X9: 0 | Y9: 0 | Z9: 0
A10: Depreciation | B10: 11916 | C10: 12527 | D10: 15744 | E10: 16382 | F10: 16988 | G10: 16110 | H10: 16780 | I10: 17012 | J10: 16950 | K10: 16830 | L10: 16780 | M10: 16934 | N10: 16750 | O10: 0 | P10: 0 | Q10: 0 | R10: 0 | S10: 0 | T10: 0 | U10: 0 | V10: 0 | W10: 0 | X10: 0 | Y10: 0 | Z10: 0
A11: Other Financial Income | B11: 2 | C11: 12.1 | D11: 3.12 | E11: 1.91 | F11: 0 | G11: 0 | H11: 0 | I11: 0 | J11: 8 | K11: 20 | L11: 22 | M11: 15.3 | N11: 18.6 | O11: 0 | P11: 0 | Q11: 0 | R11: 0 | S11: 0 | T11: 0 | U11: 0 | V11: 0 | W11: 0 | X11: 0 | Y11: 0 | Z11: 0
A12: Financial Expenses | B12: 0 | C12: ='Debt Schedule_Actual'!C7 -> 1140 | D12: ='Debt Schedule_Actual'!D7 -> 1140 | E12: ='Debt Schedule_Actual'!E7 -> 0 | F12: ='Debt Schedule_Actual'!F7 -> 190 | G12: ='Debt Schedule_Actual'!G7 -> 2470 | H12: ='Debt Schedule_Actual'!H7 -> 4940 | I12: ='Debt Schedule_Actual'!I7 -> 6650 | J12: ='Debt Schedule_Actual'!J7 -> 7980 | ... N12: ='Debt Schedule_Actual'!N7 -> 0 | O12: 0 | P12: 0 | Q12: 0 | R12: 0 | S12: 0 | T12: 0 | U12: 0 | V12: 0 | W12: 0 | X12: 0 | Y12: 0 | Z12: 0
A13: Other Expenses | B13: 824.13311 | C13: 570.23576 | D13: 39.497635 | E13: 17.395257 | F13: 67.188392 | G13: 61.587818 | H13: 26.767183 | I13: 22.805152 | J13: 68.600567 | K13: 11.28903 | L13: 75.667474 | M13: 13.047802 | N13: 15.724059 | O13: 0 | P13: 0 | Q13: 0 | R13: 0 | S13: 0 | T13: 0 | U13: 0 | V13: 0 | W13: 0 | X13: 0 | Y13: 0 | Z13: 0
A14: Other Income | B14: 0 | C14: 0 | D14: 0 | E14: 0 | F14: 0 | G14: 220.1 | H14: 35 | I14: 178 | J14: 0 | K14: 0 | L14: 0 | M14: 0 | N14: 0 | O14: 0 | P14: 0 | Q14: 0 | R14: 0 | S14: 0 | T14: 0 | U14: 0 | V14: 0 | W14: 0 | X14: 0 | Y14: 0 | Z14: 0
A15: Profit Before Tax | B15: =B5+B6-B7-B8-B9-B10+B11-B12-B13+B14 -> 17826.569 | C15: =C5+C6-C7-C8-C9-C10+C11-C12-C13+C14 -> 32761.638 | D15: =D5+D6-D7-D8-D9-D10+D11-D12-D13+D14 -> 67638.758 | E15: =E5+E6-E7-E8-E9-E10+E11-E12-E13+E14 -> 56722.073 | F15: =F5+F6-F7-F8-F9-F10+F11-F12-F13+F14 -> 26189.268 | G15: =G5+G6-G7-G8-G9-G10+G11-G12-G13+G14 -> 34307.251 | H15: =H5+H6-H7-H8-H9-H10+H11-H12-H13+H14 -> 52307.356 | I15: =I5+I6-I7-I8-I9-I10+I11-I12-I13+I14 -> 30723.664 | ... N15: =N5+N6-N7-N8-N9-N10+N11-N12-N13+N14 -> 57494.626 | O15: =O5+O6-O7-O8-O9+O11-O12-O13+O14 -> 0 | P15: =P5+P6-P7-P8-P9+P11-P12-P13+P14 -> 0 | Q15: =Q5+Q6-Q7-Q8-Q9+Q11-Q12-Q13+Q14 -> 0 | R15: =R5+R6-R7-R8-R9+R11-R12-R13+R14 -> 0 | S15: =S5+S6-S7-S8-S9+S11-S12-S13+S14 -> 0 | T15: =T5+T6-T7-T8-T9+T11-T12-T13+T14 -> 0 | U15: =U5+U6-U7-U8-U9+U11-U12-U13+U14 -> 0 | V15: =V5+V6-V7-V8-V9+V11-V12-V13+V14 -> 0 | ... Z15: =Z5+Z6-Z7-Z8-Z9+Z11-Z12-Z13+Z14 -> 0
A16: Income Tax | B16: =B15*0.18 -> 3208.7824 | C16: =C15*0.18 -> 5897.0948 | D16: =D15*0.18 -> 12174.976 | E16: =E15*0.18 -> 10209.973 | F16: =F15*0.18 -> 4714.0683 | G16: =G15*0.18 -> 6175.3051 | H16: =H15*0.18 -> 9415.3241 | I16: =I15*0.18 -> 5530.2595 | ... Z16: =Z15*0.18 -> 0
A17: Net Profit | B17: =B15-B16 -> 14617.786 | C17: =C15-C16 -> 26864.543 | D17: =D15-D16 -> 55463.782 | E17: =E15-E16 -> 46512.1 | F17: =F15-F16 -> 21475.2 | G17: =G15-G16 -> 28131.946 | H17: =H15-H16 -> 42892.032 | I17: =I15-I16 -> 25193.404 | ... Z17: =Z15-Z16 -> 0
A18: Change in Inventory | B18: 11981 | C18: ='Working Capital_Actual'!C2-'Working Capital_Actual'!B2 -> 8070.4383 | D18: ='Working Capital_Actual'!D2-'Working Capital_Actual'!C2 -> 7583.6586 | E18: ='Working Capital_Actual'!E2-'Working Capital_Actual'!D2 -> 4300.2853 | F18: ='Working Capital_Actual'!F2-'Working Capital_Actual'!E2 -> 7072.5359 | G18: ='Working Capital_Actual'!G2-'Working Capital_Actual'!F2 -> 10460.249 | H18: ='Working Capital_Actual'!H2-'Working Capital_Actual'!G2 -> 13741.607 | I18: ='Working Capital_Actual'!I2-'Working Capital_Actual'!H2 -> -6239.5803 | J18: ='Working Capital_Actual'!J2-'Working Capital_Actual'!I2 -> 13643.168 | ... N18: ='Working Capital_Actual'!N2-'Working Capital_Actual'!M2 -> 16282.146 | O18: 0 | P18: ='Working Capital_Actual'!P2-'Working Capital_Actual'!O2 -> 0 | Q18: ='Working Capital_Actual'!Q2-'Working Capital_Actual'!P2 -> 0 | R18: 0 | S18: ='Working Capital_Actual'!S2-'Working Capital_Actual'!R2 -> 0 | T18: ='Working Capital_Actual'!T2-'Working Capital_Actual'!S2 -> 0 | U18: ='Working Capital_Actual'!U2-'Working Capital_Actual'!T2 -> 0 | V18: 0 | W18: ='Working Capital_Actual'!W2-'Working Capital_Actual'!V2 -> 0 | X18: ='Working Capital_Actual'!X2-'Working Capital_Actual'!W2 -> 0 | Y18: ='Working Capital_Actual'!Y2-'Working Capital_Actual'!X2 -> 0 | Z18: 0
A19: Change in Trade Receivables | B19: 5348 | C19: ='Working Capital_Actual'!C3-'Working Capital_Actual'!B3 -> 200.0689 | D19: ='Working Capital_Actual'!D3-'Working Capital_Actual'!C3 -> -4502.7687 | E19: ='Working Capital_Actual'!E3-'Working Capital_Actual'!D3 -> 2598.6766 | F19: ='Working Capital_Actual'!F3-'Working Capital_Actual'!E3 -> 37408.604 | G19: ='Working Capital_Actual'!G3-'Working Capital_Actual'!F3 -> 13216.557 | H19: ='Working Capital_Actual'!H3-'Working Capital_Actual'!G3 -> -29965.055 | I19: ='Working Capital_Actual'!I3-'Working Capital_Actual'!H3 -> -17754.818 | J19: ='Working Capital_Actual'!J3-'Working Capital_Actual'!I3 -> -10128.373 | ... N19: ='Working Capital_Actual'!N3-'Working Capital_Actual'!M3 -> 463.17993 | O19: 0 | P19: ='Working Capital_Actual'!P3-'Working Capital_Actual'!O3 -> 0 | Q19: ='Working Capital_Actual'!Q3-'Working Capital_Actual'!P3 -> 0 | R19: ='Working Capital_Actual'!R3-'Working Capital_Actual'!Q3 -> 0 | S19: ='Working Capital_Actual'!S3-'Working Capital_Actual'!R3 -> 0 | T19: ='Working Capital_Actual'!T3-'Working Capital_Actual'!S3 -> 0 | U19: ='Working Capital_Actual'!U3-'Working Capital_Actual'!T3 -> 0 | V19: ='Working Capital_Actual'!V3-'Working Capital_Actual'!U3 -> 0 | W19: ='Working Capital_Actual'!W3-'Working Capital_Actual'!V3 -> 0 | ... Z19: ='Working Capital_Actual'!Z3-'Working Capital_Actual'!Y3 -> 0
A20: Change in Trade Payables | B20: 13551 | C20: ='Working Capital_Actual'!C4-'Working Capital_Actual'!B4 -> -33797.145 | D20: ='Working Capital_Actual'!D4-'Working Capital_Actual'!C4 -> 27892.259 | E20: ='Working Capital_Actual'!E4-'Working Capital_Actual'!D4 -> -42109.681 | F20: ='Working Capital_Actual'!F4-'Working Capital_Actual'!E4 -> 14022.46 | G20: ='Working Capital_Actual'!G4-'Working Capital_Actual'!F4 -> 13696.766 | H20: ='Working Capital_Actual'!H4-'Working Capital_Actual'!G4 -> 1433.2428 | I20: ='Working Capital_Actual'!I4-'Working Capital_Actual'!H4 -> -26317.406 | J20: ='Working Capital_Actual'!J4-'Working Capital_Actual'!I4 -> -568.03022 | ... N20: ='Working Capital_Actual'!N4-'Working Capital_Actual'!M4 -> 2605 | O20: 0 | P20: 0 | Q20: 0 | R20: 0 | S20: 0 | T20: 0 | U20: 0 | V20: 0 | W20: 0 | X20: 0 | Y20: 0 | Z20: 0
A21: Operating Cash Flow | B21: =B17+B10-B18-B19+B20-3520 -> 19235.786 | C21: =C17+C10-C18-C19+C20-B16 -> -5884.892 | D21: =D17+D10-D18-D19+D20-C16 -> 90122.056 | E21: =E17+E10-E18-E19+E20-D16 -> 1710.4801 | F21: =F17+F10-F18-F19+F20-E16 -> -2205.4522 | G21: =G17+G10-G18-G19+G20-F16 -> 29547.838 | H21: =H17+H10-H18-H19+H20-G16 -> 71153.418 | I21: =I17+I10-I18-I19+I20-H16 -> 30467.072 | J21: =J17+J10-J18-J19+J20-I16 -> 67622.118 | ... N21: =N17+N10-N18-N19+N20-M16 -> 40001.672 | O21: 0 | P21: =-P18-P19+P17+P20 -> 0 | Q21: =-Q18-Q19+Q17+Q20 -> 0 | R21: =-R18-R19+R17+R20 -> 0 | S21: =-S18-S19+S17+S20 -> 0 | T21: =-T18-T19+T17+T20 -> 0 | U21: =-U18-U19+U17+U20 -> 0 | V21: =-V18-V19+V17+V20 -> 0 | W21: =-W18-W19+W17+W20 -> 0 | ... Z21: =-Z18-Z19+Z17+Z20 -> 0
A22: Capital Expenditures | B22: =CapEx_Actual!B7 -> 15525.432 | C22: =CapEx_Actual!C7 -> 14152.348 | D22: =CapEx_Actual!D7 -> 9963.7909 | E22: =CapEx_Actual!E7 -> 8865.7923 | F22: =CapEx_Actual!F7 -> 58390.495 | G22: =CapEx_Actual!G7 -> 51725.235 | H22: =CapEx_Actual!H7 -> 41942.729 | I22: =CapEx_Actual!I7 -> 71660.09 | ... N22: =CapEx_Actual!N7 -> 296.31112 | O22: 0 | P22: 0 | Q22: 0 | R22: 0 | S22: 0 | T22: 0 | U22: 0 | V22: 0 | W22: 0 | X22: 0 | Y22: 0 | Z22: 0
A23: Cash Flow from Investing Activities | B23: =-(B22) -> -15525.432 | C23: =-C22 -> -14152.348 | D23: =-D22 -> -9963.7909 | E23: =-E22 -> -8865.7923 | F23: =-F22 -> -58390.495 | G23: =-G22 -> -51725.235 | H23: =-H22 -> -41942.729 | I23: =-I22 -> -71660.09 | J23: =-J22 -> -26860.911 | ... Z23: =-Z22 -> 0
A24: Charge in Share Capital | B24: 0 | C24: 0 | D24: 0 | E24: 0 | F24: 0 | G24: 0 | H24: 0 | I24: 0 | J24: 0 | K24: 0 | L24: 0 | M24: 0 | N24: 0 | O24: 0 | P24: 0 | Q24: 0 | R24: 0 | S24: 0 | T24: 0 | U24: 0 | V24: 0 | W24: 0 | X24: 0 | Y24: 0 | Z24: 0
A25: Target Financing | B25: 0 | C25: 0 | D25: 0 | E25: 0 | F25: 0 | G25: 0 | H25: 0 | I25: 0 | J25: 0 | K25: 0 | L25: 0 | M25: 0 | N25: 0 | O25: 0 | P25: 0 | Q25: 0 | R25: 0 | S25: 0 | T25: 0 | U25: 0 | V25: 0 | W25: 0 | X25: 0 | Y25: 0 | Z25: 0
A26: Loans from Shareholders | B26: 0 | C26: 0 | D26: 0 | E26: 0 | F26: 0 | G26: 0 | H26: 0 | I26: 0 | J26: 0 | K26: 0 | L26: 0 | M26: 0 | N26: 0 | O26: 0 | P26: 0 | Q26: 0 | R26: 0 | S26: 0 | T26: 0 | U26: 0 | V26: 0 | W26: 0 | X26: 0 | Y26: 0 | Z26: 0
A27: Prepayment of Sharholders Loans | B27: 0 | C27: 0 | D27: 0 | E27: 0 | F27: 0 | G27: 0 | H27: 0 | I27: 0 | J27: 0 | K27: 0 | L27: 0 | M27: 0 | N27: 0 | O27: 0 | P27: 0 | Q27: 0 | R27: 0 | S27: 0 | T27: 0 | U27: 0 | V27: 0 | W27: 0 | X27: 0 | Y27: 0 | Z27: 0
A28: Proceeds from Borrowings | B28: ='Debt Schedule_Actual'!B3 -> 0 | C28: ='Debt Schedule_Actual'!C3 -> 12000 | D28: ='Debt Schedule_Actual'!D3 -> 0 | E28: ='Debt Schedule_Actual'!E3 -> 0 | F28: ='Debt Schedule_Actual'!F3 -> 2000 | G28: ='Debt Schedule_Actual'!G3 -> 22000 | H28: ='Debt Schedule_Actual'!H3 -> 4000 | I28: ='Debt Schedule_Actual'!I3 -> 14000 | ... Z28: ='Debt Schedule_Actual'!Z3 -> 0
A29: Repayment of Borrowings | B29: ='Debt Schedule_Actual'!B4 -> 0 | C29: ='Debt Schedule_Actual'!C4 -> 0 | D29: ='Debt Schedule_Actual'!D4 -> 12000 | E29: ='Debt Schedule_Actual'!E4 -> 0 | F29: ='Debt Schedule_Actual'!F4 -> 0 | G29: ='Debt Schedule_Actual'!G4 -> 0 | H29: ='Debt Schedule_Actual'!H4 -> 0 | I29: ='Debt Schedule_Actual'!I4 -> 0 | ... Z29: ='Debt Schedule_Actual'!Z4 -> 0
A30: Other | B30: 0 | C30: 0 | D30: 0 | E30: 0 | F30: 0 | G30: 0 | H30: 0 | I30: 0 | J30: 0 | K30: 0 | L30: 0 | M30: 0 | N30: 0 | O30: 0 | P30: 0 | Q30: 0 | R30: 0 | S30: 0 | T30: 0 | U30: 0 | V30: 0 | W30: 0 | X30: 0 | Y30: 0 | Z30: 0
A31: Cash Flow from Financng Activities | B31: =B24+B26-B27+B30+B28-B29 -> 0 | C31: =C24+C26-C27+C30+C28-C29 -> 12000 | D31: =D24+D26-D27+D30+D28-D29 -> -12000 | E31: =E24+E26-E27+E30+E28-E29 -> 0 | F31: =F24+F26-F27+F30+F28-F29 -> 2000 | G31: =G24+G26-G27+G30+G28-G29 -> 22000 | H31: =H24+H26-H27+H30+H28-H29-H30 -> 4000 | I31: =I24+I25-I27+I28-I29 -> 14000 | J31: =J24+J25-J27+J28-J29 -> 0 | K31: =K24+K26-K27+K30+K28-K29 -> -10000 | L31: =L24+L26-L27+L30+L28-L29 -> -32000 | M31: =M24+M26-M27+M30+M28-M29 -> 0 | N31: =N24+N26-N27+N30+N28-N29 -> 0 | O31: =O24+O26-O27+O30+O28-O29 -> 0 | P31: =P24+P26-P27+P30+P28-P29 -> 0 | Q31: =Q24+Q26-Q27+Q30+Q28-Q29 -> 0 | R31: =R24+R26-R27+R30+R28-R29 -> 0 | ... Z31: =Z24+Z26-Z27+Z30+Z28-Z29 -> 0
A32: Net Cash Flow | B32: =B21+B23+B31 -> 3710.354 | C32: =C21+C23+C31 -> -8037.24 | D32: =D21+D23+D31 -> 68158.265 | E32: =E21+E23+E31 -> -7155.3122 | F32: =F21+F23+F31 -> -58595.947 | G32: =G21+G23+G31 -> -177.39742 | H32: =H21+H23+H31 -> 33210.689 | I32: =I21+I23+I31 -> -27193.018 | ... Z32: =Z21+Z23+Z31 -> 0
A33: Closing Cash Balance | B33: =B32+B2 -> 9007.354 | C33: =C32+C2 -> 970.11401 | D33: =D32+D2 -> 69128.379 | E33: =E32+E2 -> 61973.067 | F33: =F32+F2 -> 3377.1199 | G33: =G32+G2 -> 3199.7225 | H33: =H32+H2 -> 36410.411 | I33: =I32+I2 -> 9217.393 | ... Z33: =Z32+Z2 -> 0

Sheet Sales_Actual
A1: Indicator | B1: 44835 | C1: 44927 | D1: 45017 | E1: 45108 | F1: 45200 | G1: 45292 | H1: 45383 | I1: 45474 | J1: 45566 | K1: 45658 | L1: 45748 | M1: 45839 | N1: 45931 | O1: 46023 | P1: 46113 | Q1: 46204 | R1: 46296 | S1: 46388 | T1: 46478 | U1: 46569 | V1: 46661 | W1: 46753 | X1: 46844 | Y1: 46935 | Z1: 47027
A2: Business Line A
A3: Volume, ths.m2 | B3: 183.8424 | C3: 503.4 | D3: 729.45 | E3: 673.5432 | F3: 311.3392 | G3: 860.188 | H3: 949.592 | I3: 681.2374 | J3: 296.10084 | K3: 796.3838 | L3: 946.65072 | M3: 763.4432 | N3: 763.4432 | O3: 0 | P3: 0 | Q3: 0 | R3: 0 | S3: 0 | T3: 0 | U3: 0 | V3: 0 | W3: 0 | X3: 0 | Y3: 0 | Z3: 0
A4: Price, UAH | B4: 72.14 | C4: 72.46 | D4: 73.1 | E4: 73.59 | F4: 73.8 | G4: 74.5 | H4: 75.1 | I4: 76.8 | J4: 76.7 | K4: 77.3 | L4: 83.4 | M4: 83.6 | N4: 84.5 | O4: 0 | P4: 0 | Q4: 0 | R4: 0 | S4: 0 | T4: 0 | U4: 0 | V4: 0 | W4: 0 | X4: 0 | Y4: 0 | Z4: 0
A5: Revenue (excl. VAT), ths. UAH | B5: =B3*B4 -> 13262.391 | C5: =C3*C4 -> 36476.364 | D5: =D3*D4 -> 53322.795 | E5: =E3*E4 -> 49566.044 | F5: =F3*F4 -> 22976.833 | G5: =G3*G4 -> 64084.006 | H5: =H3*H4 -> 71314.359 | I5: =I3*I4 -> 52319.032 | ... N5: =N3*N4 -> 64510.95 | O5: 0 | P5: 0 | Q5: 0 | R5: 0 | S5: 0 | T5: 0 | U5: 0 | V5: 0 | W5: 0 | X5: 0 | Y5: 0 | Z5: 0
A6: Business Line B
A7: Volume, ths.m2 | B7: 36.8032 | C7: 195.12268 | D7: 243.72448 | E7: 145.018 | F7: 60.946 | G7: 122.016 | H7: 199.764 | I7: 107.136 | J7: 88.84724 | K7: 175.64476 | L7: 200.21164 | M7: 105.8774 | N7: 105.8774 | O7: 0 | P7: 0 | Q7: 0 | R7: 0 | S7: 0 | T7: 0 | U7: 0 | V7: 0 | W7: 0 | X7: 0 | Y7: 0 | Z7: 0
A8: Price, UAH | B8: 209.65273 | C8: 211.45 | D8: 216.4 | E8: 224.01112 | F8: 230.12208 | G8: 236.4 | H8: 237.1 | I8: 238.4 | J8: 227.02778 | K8: 238.12 | L8: 242.4 | M8: 235.45376 | N8: 235.89272 | O8: 0 | P8: 0 | Q8: 0 | R8: 0 | S8: 0 | T8: 0 | U8: 0 | V8: 0 | W8: 0 | X8: 0 | Y8: 0 | Z8: 0
A9: Revenue (excl. VAT), ths. UAH | B9: =B7*B8 -> 7715.8915 | C9: =C7*C8 -> 41258.691 | D9: =D7*D8 -> 52741.977 | E9: =E7*E8 -> 32485.644 | F9: =F7*F8 -> 14025.02 | G9: =G7*G8 -> 28844.582 | H9: =H7*H8 -> 47364.044 | I9: =I7*I8 -> 25541.222 | ... N9: =N7*N8 -> 24975.708 | O9: 0 | P9: 0 | Q9: 0 | R9: 0 | S9: 0 | T9: 0 | U9: 0 | V9: 0 | W9: 0 | X9: 0 | Y9: 0 | Z9: 0
A10: Business Line C
A11: Volume, ths.m2 | B11: 6174.1336 | C11: 9363.6765 | D11: 11737.27 | E11: 9610.2232 | F11: 13343.795 | G11: 9992.9194 | H11: 8709.4178 | I11: 9558.6578 | J11: 6465.1802 | K11: 9626.1113 | L11: 11881.178 | M11: 7827.8088 | N11: 7827.8088 | O11: 0 | P11: 0 | Q11: 0 | R11: 0 | S11: 0 | T11: 0 | U11: 0 | V11: 0 | W11: 0 | X11: 0 | Y11: 0 | Z11: 0
A12: Price, UAH | B12: 14.811034 | C12: 15.547899 | D12: 15.804016 | E12: 14.295891 | F12: 11.367838 | G12: 16.024907 | H12: 19.080323 | I12: 16.900394 | J12: 20.956488 | K12: 15.888515 | L12: 19.701759 | M12: 20.000595 | N12: 15.966256 | O12: 0 | P12: 0 | Q12: 0 | R12: 0 | S12: 0 | T12: 0 | U12: 0 | V12: 0 | W12: 0 | X12: 0 | Y12: 0 | Z12: 0
A13: Revenue (excl. VAT), ths. UAH | B13: =B11*B12 -> 91445.3 | C13: =C11*C12 -> 145585.5 | D13: =D11*D12 -> 185496 | E13: =E11*E12 -> 137386.7 | F13: =F11*F12 -> 151690.1 | G13: =G11*G12 -> 160135.6 | H13: =H11*H12 -> 166178.5 | I13: =I11*I12 -> 161545.08 | ... N13: =N11*N12 -> 124980.8 | O13: 0 | P13: 0 | Q13: 0 | R13: 0 | S13: 0 | T13: 0 | U13: 0 | V13: 0 | W13: 0 | X13: 0 | Y13: 0 | Z13: 0
A14: Business Line D
A15: Volume, ths.m2 | B15: 0 | C15: 0 | D15: 0 | E15: 0 | F15: 0 | G15: 0 | H15: 231.88 | I15: 107.88 | J15: 149.56632 | K15: 1039.4883 | L15: 508.648 | M15: 136.59344 | N15: 136.59344 | O15: 0 | P15: 0 | Q15: 0 | R15: 0 | S15: 0 | T15: 0 | U15: 0 | V15: 0 | W15: 0 | X15: 0 | Y15: 0 | Z15: 0
A16: Price, UAH | B16: 0 | C16: 0 | D16: 0 | E16: 0 | F16: 0 | G16: 0 | H16: 0 | I16: 10.988506 | J16: 10.988506 | K16: 14.038884 | L16: 14.038884 | M16: 17.968552 | N16: 22.143142 | O16: 0 | P16: 0 | Q16: 0 | R16: 0 | S16: 0 | T16: 0 | U16: 0 | V16: 0 | W16: 0 | X16: 0 | Y16: 0 | Z16: 0
A17: Revenue (excl. VAT), ths. UAH | B17: =B15*B16 -> 0 | C17: =C15*C16 -> 0 | D17: =D15*D16 -> 0 | E17: =E15*E16 -> 0 | F17: =F15*F16 -> 0 | G17: =G15*G16 -> 0 | H17: =H15*H16 -> 0 | I17: =I15*I16 -> 1185.44 | ... Z17: =Z15*Z16 -> 0
A18: Business Line E
A19: Volume, t | B19: 206.19092 | C19: 151.85412 | D19: 172.01528 | E19: 258.8252 | F19: 268.8816 | G19: 262.756 | H19: 144.832 | I19: 229.772 | J19: 142.724 | K19: 174.19049 | L19: 154.32916 | M19: 71.43392 | N19: 71.43392 | O19: 0 | P19: 0 | Q19: 0 | R19: 0 | S19: 0 | T19: 0 | U19: 0 | V19: 0 | W19: 0 | X19: 0 | Y19: 0 | Z19: 0
A20: Price, UAH | B20: 76.61156 | C20: 65.65085 | D20: 63.279076 | E20: 58.675322 | F20: 50.428426 | G20: 58.141576 | H20: 63.706336 | I20: 64.95136 | J20: 64.95136 | K20: 66.137894 | L20: 66.137894 | M20: 67.577274 | N20: 61.543536 | O20: 0 | P20: 0 | Q20: 0 | R20: 0 | S20: 0 | T20: 0 | U20: 0 | V20: 0 | W20: 0 | X20: 0 | Y20: 0 | Z20: 0
A21: Revenue (excl. VAT), ths. UAH | B21: =B19*B20 -> 15796.608 | C21: =C19*C20 -> 9969.352 | D21: =D19*D20 -> 10884.968 | E21: =E19*E20 -> 15186.652 | F21: =F19*F20 -> 13559.276 | G21: =G19*G20 -> 15277.048 | H21: =H19*H20 -> 9226.716 | I21: =I19*I20 -> 14924.004 | ... N21: =N19*N20 -> 4396.296 | O21: 0 | P21: 0 | Q21: 0 | R21: 0 | S21: 0 | T21: 0 | U21: 0 | V21: 0 | W21: 0 | X21: 0 | Y21: 0 | Z21: 0
A22: Business Line F
A23: Volume, t | B23: 134.9988 | C23: 184.84432 | D23: 256.4506 | E23: 229.152 | F23: 276.7556 | G23: 196.6144 | H23: 244.776 | I23: 140.368 | J23: 160.332 | K23: 209.1136 | L23: 79.732 | M23: 136.648 | N23: 136.648 | O23: 0 | P23: 0 | Q23: 0 | R23: 0 | S23: 0 | T23: 0 | U23: 0 | V23: 0 | W23: 0 | X23: 0 | Y23: 0 | Z23: 0
A24: Price, UAH | B24: 36.973455 | C24: 38.149703 | D24: 37.770471 | E24: 38.731602 | F24: 28.850307 | G24: 38.659813 | H24: 42.153495 | I24: 38.990283 | J24: 38.990283 | K24: 38.261978 | L24: 38.261978 | M24: 36.363919 | N24: 42.317604 | O24: 0 | P24: 0 | Q24: 0 | R24: 0 | S24: 0 | T24: 0 | U24: 0 | V24: 0 | W24: 0 | X24: 0 | Y24: 0 | Z24: 0
A25: Revenue (excl. VAT), ths. UAH | B25: =B23*B24 -> 4991.372 | C25: =C23*C24 -> 7051.756 | D25: =D23*D24 -> 9686.26 | E25: =E23*E24 -> 8875.424 | F25: =F23*F24 -> 7984.484 | G25: =G23*G24 -> 7601.076 | H25: =H23*H24 -> 10318.164 | I25: =I23*I24 -> 5472.988 | ... N25: =N23*N24 -> 5782.616 | O25: 0 | P25: 0 | Q25: 0 | R25: 0 | S25: 0 | T25: 0 | U25: 0 | V25: 0 | W25: 0 | X25: 0 | Y25: 0 | Z25: 0
A26: Business Line G
A27: Volume, ths.m2 | B27: 0 | C27: 1.1904 | D27: 150.164 | E27: 89.70532 | F27: 82.1128 | G27: 325.872 | H27: 399.342 | I27: 484.716 | J27: 261.9128 | K27: 648.0736 | L27: 848.3088 | M27: 727.88 | N27: 727.88 | O27: 0 | P27: 0 | Q27: 0 | R27: 0 | S27: 0 | T27: 0 | U27: 0 | V27: 0 | W27: 0 | X27: 0 | Y27: 0 | Z27: 0
A28: Price, UAH | B28: 0 | C28: 25 | D28: 27.275805 | E28: 61.791742 | F28: 35.726367 | G28: 25.309741 | H28: 24.272628 | I28: 24.056536 | J28: 24.056536 | K28: 24.175149 | L28: 24.175149 | M28: 23.175759 | N28: 25.617036 | O28: 0 | P28: 0 | Q28: 0 | R28: 0 | S28: 0 | T28: 0 | U28: 0 | V28: 0 | W28: 0 | X28: 0 | Y28: 0 | Z28: 0
A29: Revenue (excl. VAT), ths. UAH | B29: =B27*B28 -> 0 | C29: =C27*C28 -> 29.76 | D29: =D27*D28 -> 4095.844 | E29: =E27*E28 -> 5543.048 | F29: =F27*F28 -> 2933.592 | G29: =G27*G28 -> 8247.736 | H29: =H27*H28 -> 9693.08 | I29: =I27*I28 -> 11660.588 | ... N29: =N27*N28 -> 18646.128 | O29: 0 | P29: 0 | Q29: 0 | R29: 0 | S29: 0 | T29: 0 | U29: 0 | V29: 0 | W29: 0 | X29: 0 | Y29: 0 | Z29: 0
A30: Business Line H
A31: Volume, t | B31: 30.10844 | C31: 0 | D31: 21.78184 | E31: 0 | F31: 0 | G31: 0 | H31: 0 | I31: 0 | J31: 0 | K31: 282.69148 | L31: 574.88508 | M31: 174.42584 | N31: 174.42584 | O31: 0 | P31: 0 | Q31: 0 | R31: 0 | S31: 0 | T31: 0 | U31: 0 | V31: 0 | W31: 0 | X31: 0 | Y31: 0 | Z31: 0
A32: Price, UAH | B32: 48.002487 | C32: 0 | D32: 35.397928 | E32: 0 | F32: 0 | G32: 0 | H32: 0 | I32: 0 | J32: 0 | K32: 53.057545 | L32: 51.848832 | M32: 47.114441 | N32: 47.114441 | O32: 0 | P32: 0 | Q32: 0 | R32: 0 | S32: 0 | T32: 0 | U32: 0 | V32: 0 | W32: 0 | X32: 0 | Y32: 0 | Z32: 0
A33: Revenue (excl. VAT), ths. UAH | B33: =B31*B32 -> 1445.28 | C33: =C31*C32 -> 0 | D33: =D31*D32 -> 771.032 | E33: =E31*E32 -> 0 | F33: =F31*F32 -> 0 | G33: =G31*G32 -> 0 | H33: =H31*H32 -> 0 | I33: =I31*I32 -> 0 | ... N33: =N31*N32 -> 8217.976 | O33: 0 | P33: 0 | Q33: 0 | R33: 0 | S33: 0 | T33: 0 | U33: 0 | V33: 0 | W33: 0 | X33: 0 | Y33: 0 | Z33: 0
A34: Other
A35: Revenue (excl. VAT), ths. UAH | B35: 778.844 | C35: 4191.076 | D35: 4837.24 | E35: 2657.072 | F35: 3103.1 | G35: 4662.4 | H35: 5135.336 | I35: 3453.648 | J35: 1095.292 | K35: 4736.428 | L35: 6058.888 | M35: 2990.756 | N35: 2990.756 | O35: 0 | P35: 0 | Q35: 0 | R35: 0 | S35: 0 | T35: 0 | U35: 0 | V35: 0 | W35: 0 | X35: 0 | Y35: 0 | Z35: 0
A36: Total | B36: =B5+B9+B13+B17+B21+B25+B29+B33+B35 -> 135435.69 | C36: =C5+C9+C13+C17+C21+C25+C29+C33+C35 -> 244562.5 | D36: =D5+D9+D13+D17+D21+D25+D29+D33+D35 -> 321836.12 | E36: =E5+E9+E13+E17+E21+E25+E29+E33+E35 -> 251700.58 | F36: =F5+F9+F13+F17+F21+F25+F29+F33+F35 -> 216272.4 | G36: =G5+G9+G13+G17+G21+G25+G29+G33+G35 -> 288852.45 | H36: =H5+H9+H13+H17+H21+H25+H29+H33+H35 -> 319230.2 | I36: =I5+I9+I13+I17+I21+I25+I29+I33+I35 -> 276102 | ... Z36: =Z5+Z9+Z13+Z17+Z21+Z25+Z29+Z33+Z35 -> 0

Sheet COGS_Actual
A1: Indicator | B1: 44835 | C1: 44927 | D1: 45017 | E1: 45108 | F1: 45200 | G1: 45292 | H1: 45383 | I1: 45474 | J1: 45566 | K1: 45658 | L1: 45748 | M1: 45839 | N1: 45931 | O1: 46023 | P1: 46113 | Q1: 46204 | R1: 46296 | S1: 46388 | T1: 46478 | U1: 46569 | V1: 46661 | W1: 46753 | X1: 46844 | Y1: 46935 | Z1: 47027
A2: Business Line A
A3: Volume, ths.m2 | B3: =Sales_Actual!B3 -> 183.8424 | C3: =Sales_Actual!C3 -> 503.4 | D3: =Sales_Actual!D3 -> 729.45 | E3: =Sales_Actual!E3 -> 673.5432 | F3: =Sales_Actual!F3 -> 311.3392 | G3: =Sales_Actual!G3 -> 860.188 | H3: =Sales_Actual!H3 -> 949.592 | I3: =Sales_Actual!I3 -> 681.2374 | ... N3: =Sales_Actual!N3 -> 763.4432 | O3: 0 | P3: 0 | Q3: 0 | R3: 0 | S3: 0 | T3: 0 | U3: 0 | V3: 0 | W3: 0 | X3: 0 | Y3: 0 | Z3: 0
A4: Unit Cost, UAH | B4: 50.32928 | C4: 44.288742 | D4: 42.891581 | E4: 41.604516 | F4: 45.695637 | G4: 51.456934 | H4: 40.180652 | I4: 45.493921 | J4: 43.386303 | K4: 49.150415 | L4: 56.002597 | M4: 51.026515 | N4: 47.373709 | O4: 0 | P4: 0 | Q4: 0 | R4: 0 | S4: 0 | T4: 0 | U4: 0 | V4: 0 | W4: 0 | X4: 0 | Y4: 0 | Z4: 0
A5: COGS, ths. UAN | B5: =B3*B4 -> 9252.6556 | C5: =C3*C4 -> 22294.953 | D5: =D3*D4 -> 31287.264 | E5: =E3*E4 -> 28022.439 | F5: =F3*F4 -> 14226.843 | G5: =G3*G4 -> 44262.637 | H5: =H3*H4 -> 38155.226 | I5: =I3*I4 -> 30992.16 | ... N5: =N3*N4 -> 36167.136 | O5: 0 | P5: 0 | Q5: 0 | R5: 0 | S5: 0 | T5: 0 | U5: 0 | V5: 0 | W5: 0 | X5: 0 | Y5: 0 | Z5: 0
A6: Business Line B
A7: Volume, ths.m2 | B7: =Sales_Actual!B7 -> 36.8032 | C7: =Sales_Actual!C7 -> 195.12268 | D7: =Sales_Actual!D7 -> 243.72448 | E7: =Sales_Actual!E7 -> 145.018 | F7: =Sales_Actual!F7 -> 60.946 | G7: =Sales_Actual!G7 -> 122.016 | H7: =Sales_Actual!H7 -> 199.764 | I7: =Sales_Actual!I7 -> 107.136 | ... N7: =Sales_Actual!N7 -> 105.8774 | O7: 0 | P7: 0 | Q7: 0 | R7: 0 | S7: 0 | T7: 0 | U7: 0 | V7: 0 | W7: 0 | X7: 0 | Y7: 0 | Z7: 0
A8: Unit Cost, UAH | B8: 152.94879 | C8: 171.9103 | D8: 172.45 | E8: 176.48 | F8: 176.9 | G8: 178 | H8: 179.3 | I8: 183.6 | J8: 185.4 | K8: 184.5 | L8: 186.4 | M8: 187.1 | N8: 189.2 | O8: 0 | P8: 0 | Q8: 0 | R8: 0 | S8: 0 | T8: 0 | U8: 0 | V8: 0 | W8: 0 | X8: 0 | Y8: 0 | Z8: 0
A9: COGS, ths. UAN | B9: =B7*B8 -> 5629.005 | C9: =C7*C8 -> 33543.599 | D9: =D7*D8 -> 42030.287 | E9: =E7*E8 -> 25592.777 | F9: =F7*F8 -> 10781.347 | G9: =G7*G8 -> 21718.848 | H9: =H7*H8 -> 35817.685 | I9: =I7*I8 -> 19670.17 | ... N9: =N7*N8 -> 20032.004 | O9: 0 | P9: 0 | Q9: 0 | R9: 0 | S9: 0 | T9: 0 | U9: 0 | V9: 0 | W9: 0 | X9: 0 | Y9: 0 | Z9: 0
A10: Business Line C
A11: Volume, ths.m2 | B11: =Sales_Actual!B11 -> 6174.1336 | C11: =Sales_Actual!C11 -> 9363.6765 | D11: =Sales_Actual!D11 -> 11737.27 | E11: =Sales_Actual!E11 -> 9610.2232 | F11: =Sales_Actual!F11 -> 13343.795 | G11: =Sales_Actual!G11 -> 9992.9194 | H11: =Sales_Actual!H11 -> 8709.4178 | I11: =Sales_Actual!I11 -> 9558.6578 | ... N11: =Sales_Actual!N11 -> 7827.8088 | O11: 0 | P11: 0 | Q11: 0 | R11: 0 | S11: 0 | T11: 0 | U11: 0 | V11: 0 | W11: 0 | X11: 0 | Y11: 0 | Z11: 0
A12: Unit Cost, UAH | B12: 9.3977345 | C12: 10.421058 | D12: 9.9644114 | E12: 8.7311277 | F12: 7.5983855 | G12: 10.132212 | H12: 13.05982 | I12: 11.959832 | J12: 10.366706 | K12: 9.7027915 | L12: 12.779155 | M12: 13.34591 | N12: 9.9607178 | O12: 0 | P12: 0 | Q12: 0 | R12: 0 | S12: 0 | T12: 0 | U12: 0 | V12: 0 | W12: 0 | X12: 0 | Y12: 0 | Z12: 0
A13: COGS, ths. UAN | B13: =B11*B12 -> 58022.868 | C13: =C11*C12 -> 97579.414 | D13: =D11*D12 -> 116954.98 | E13: =E11*E12 -> 83908.086 | F13: =F11*F12 -> 101391.3 | G13: =G11*G12 -> 101250.38 | H13: =H11*H12 -> 113743.43 | I13: =I11*I12 -> 114319.94 | ... N13: =N11*N12 -> 77970.594 | O13: 0 | P13: 0 | Q13: 0 | R13: 0 | S13: 0 | T13: 0 | U13: 0 | V13: 0 | W13: 0 | X13: 0 | Y13: 0 | Z13: 0
A14: Business Line D
A15: Volume, ths.m2 | B15: =Sales_Actual!B15 -> 0 | C15: =Sales_Actual!C15 -> 0 | D15: =Sales_Actual!D15 -> 0 | E15: =Sales_Actual!E15 -> 0 | F15: =Sales_Actual!F15 -> 0 | G15: =Sales_Actual!G15 -> 0 | H15: =Sales_Actual!H15 -> 231.88 | I15: =Sales_Actual!I15 -> 107.88 | ... N15: =Sales_Actual!N15 -> 136.59344 | O15: 0 | P15: 0 | Q15: 0 | R15: 0 | S15: 0 | T15: 0 | U15: 0 | V15: 0 | W15: 0 | X15: 0 | Y15: 0 | Z15: 0
A16: Unit Cost, UAH | B16: 0 | C16: 0 | D16: 0 | E16: 0 | F16: 0 | G16: 0 | H16: 7.1430502 | I16: 5.4279959 | J16: 9.3963678 | K16: 6.6448833 | L16: 10.313507 | M16: 10.604583 | N16: 10.37623 | O16: 0 | P16: 0 | Q16: 0 | R16: 0 | S16: 0 | T16: 0 | U16: 0 | V16: 0 | W16: 0 | X16: 0 | Y16: 0 | Z16: 0
A17: COGS, ths. UAN | B17: =B15*B16 -> 0 | C17: =C15*C16 -> 0 | D17: =D15*D16 -> 0 | E17: =E15*E16 -> 0 | F17: =F15*F16 -> 0 | G17: =G15*G16 -> 0 | H17: =H15*H16 -> 1656.3305 | I17: =I15*I16 -> 585.57219 | ... N17: =N15*N16 -> 1417.325 | O17: 0 | P17: 0 | Q17: 0 | R17: 0 | S17: 0 | T17: 0 | U17: 0 | V17: 0 | W17: 0 | X17: 0 | Y17: 0 | Z17: 0
A18: Business Line E
A19: Volume, t | B19: =Sales_Actual!B19 -> 206.19092 | C19: =Sales_Actual!C19 -> 151.85412 | D19: =Sales_Actual!D19 -> 172.01528 | E19: =Sales_Actual!E19 -> 258.8252 | F19: =Sales_Actual!F19 -> 268.8816 | G19: =Sales_Actual!G19 -> 262.756 | H19: =Sales_Actual!H19 -> 144.832 | I19: =Sales_Actual!I19 -> 229.772 | ... N19: =Sales_Actual!N19 -> 71.43392 | O19: 0 | P19: 0 | Q19: 0 | R19: 0 | S19: 0 | T19: 0 | U19: 0 | V19: 0 | W19: 0 | X19: 0 | Y19: 0 | Z19: 0
A20: Unit Cost, UAH | B20: 56.983497 | C20: 44.023165 | D20: 48.188523 | E20: 44.671984 | F20: 33.455817 | G20: 45.01425 | H20: 47.081086 | I20: 51.827035 | J20: 44.734236 | K20: 45.924547 | L20: 46.881647 | M20: 46.835873 | N20: 42.303382 | O20: 0 | P20: 0 | Q20: 0 | R20: 0 | S20: 0 | T20: 0 | U20: 0 | V20: 0 | W20: 0 | X20: 0 | Y20: 0 | Z20: 0
A21: COGS, ths. UAN | B21: =B19*B20 -> 11749.48 | C21: =C19*C20 -> 6685.099 | D21: =D19*D20 -> 8289.1622 | E21: =E19*E20 -> 11562.235 | F21: =F19*F20 -> 8995.6535 | G21: =G19*G20 -> 11827.764 | H21: =H19*H20 -> 6818.8479 | I21: =I19*I20 -> 11908.401 | ... N21: =N19*N20 -> 3021.8964 | O21: 0 | P21: 0 | Q21: 0 | R21: 0 | S21: 0 | T21: 0 | U21: 0 | V21: 0 | W21: 0 | X21: 0 | Y21: 0 | Z21: 0
A22: Business Line F
A23: Volume, t | B23: =Sales_Actual!B23 -> 134.9988 | C23: =Sales_Actual!C23 -> 184.84432 | D23: =Sales_Actual!D23 -> 256.4506 | E23: =Sales_Actual!E23 -> 229.152 | F23: =Sales_Actual!F23 -> 276.7556 | G23: =Sales_Actual!G23 -> 196.6144 | H23: =Sales_Actual!H23 -> 244.776 | I23: =Sales_Actual!I23 -> 140.368 | ... N23: =Sales_Actual!N23 -> 136.648 | O23: 0 | P23: 0 | Q23: 0 | R23: 0 | S23: 0 | T23: 0 | U23: 0 | V23: 0 | W23: 0 | X23: 0 | Y23: 0 | Z23: 0
A24: Unit Cost, UAH | B24: 24.114688 | C24: 25.439823 | D24: 26.234315 | E24: 26.882158 | F24: 18.885686 | G24: 25.874456 | H24: 27.785583 | I24: 25.413154 | J24: 24.803735 | K24: 24.896717 | L24: 24.114738 | M24: 27.610786 | N24: 29.179827 | O24: 0 | P24: 0 | Q24: 0 | R24: 0 | S24: 0 | T24: 0 | U24: 0 | V24: 0 | W24: 0 | X24: 0 | Y24: 0 | Z24: 0
A25: COGS, ths. UAN | B25: =B23*B24 -> 3255.454 | C25: =C23*C24 -> 4702.4067 | D25: =D23*D24 -> 6727.8059 | E25: =E23*E24 -> 6160.1002 | F25: =F23*F24 -> 5226.7194 | G25: =G23*G24 -> 5087.2906 | H25: =H23*H24 -> 6801.2438 | I25: =I23*I24 -> 3567.1936 | ... N25: =N23*N24 -> 3987.365 | O25: 0 | P25: 0 | Q25: 0 | R25: 0 | S25: 0 | T25: 0 | U25: 0 | V25: 0 | W25: 0 | X25: 0 | Y25: 0 | Z25: 0
A26: Business Line G
A27: Volume, ths.m2 | B27: =Sales_Actual!B27 -> 0 | C27: =Sales_Actual!C27 -> 1.1904 | D27: =Sales_Actual!D27 -> 150.164 | E27: =Sales_Actual!E27 -> 89.70532 | F27: =Sales_Actual!F27 -> 82.1128 | G27: =Sales_Actual!G27 -> 325.872 | H27: =Sales_Actual!H27 -> 399.342 | I27: =Sales_Actual!I27 -> 484.716 | ... N27: =Sales_Actual!N27 -> 727.88 | O27: 0 | P27: 0 | Q27: 0 | R27: 0 | S27: 0 | T27: 0 | U27: 0 | V27: 0 | W27: 0 | X27: 0 | Y27: 0 | Z27: 0
A28: Unit Cost, UAH | B28: 0 | C28: 11.6726 | D28: 12.763241 | E28: 30.302526 | F28: 16.519415 | G28: 12.664987 | H28: 10.974599 | I28: 12.531751 | J28: 11.469439 | K28: 11.61497 | L28: 10.763898 | M28: 12.779501 | N28: 12.671276 | O28: 0 | P28: 0 | Q28: 0 | R28: 0 | S28: 0 | T28: 0 | U28: 0 | V28: 0 | W28: 0 | X28: 0 | Y28: 0 | Z28: 0
A29: COGS, ths. UAN | B29: =B27*B28 -> 0 | C29: =C27*C28 -> 13.895063 | D29: =D27*D28 -> 1916.5794 | E29: =E27*E28 -> 2718.2978 | F29: =F27*F28 -> 1356.4554 | G29: =G27*G28 -> 4127.1647 | H29: =H27*H28 -> 4382.6183 | I29: =I27*I28 -> 6074.3404 | ... N29: =N27*N28 -> 9223.168 | O29: 0 | P29: 0 | Q29: 0 | R29: 0 | S29: 0 | T29: 0 | U29: 0 | V29: 0 | W29: 0 | X29: 0 | Y29: 0 | Z29: 0
A30: Business Line H
A31: Volume, t | B31: =Sales_Actual!B31 -> 30.10844 | C31: =Sales_Actual!C31 -> 0 | D31: =Sales_Actual!D31 -> 21.78184 | E31: =Sales_Actual!E31 -> 0 | F31: =Sales_Actual!F31 -> 0 | G31: =Sales_Actual!G31 -> 0 | H31: =Sales_Actual!H31 -> 0 | I31: =Sales_Actual!I31 -> 0 | ... N31: =Sales_Actual!N31 -> 174.42584 | O31: 0 | P31: 0 | Q31: 0 | R31: 0 | S31: 0 | T31: 0 | U31: 0 | V31: 0 | W31: 0 | X31: 0 | Y31: 0 | Z31: 0
A32: Unit Cost, UAH | B32: 29.362874 | C32: 0 | D32: 24.616361 | E32: 0 | F32: 0 | G32: 0 | H32: 0 | I32: 0 | J32: 0 | K32: 34.362141 | L32: 34.060226 | M32: 28.93243 | N32: 31.591245 | O32: 0 | P32: 0 | Q32: 0 | R32: 0 | S32: 0 | T32: 0 | U32: 0 | V32: 0 | W32: 0 | X32: 0 | Y32: 0 | Z32: 0
A33: COGS, ths. UAN | B33: =B31*B32 -> 884.07032 | C33: =C31*C32 -> 0 | D33: =D31*D32 -> 536.18965 | E33: =E31*E32 -> 0 | F33: =F31*F32 -> 0 | G33: =G31*G32 -> 0 | H33: =H31*H32 -> 0 | I33: =I31*I32 -> 0 | ... N33: =N31*N32 -> 5510.3294 | O33: 0 | P33: 0 | Q33: 0 | R33: 0 | S33: 0 | T33: 0 | U33: 0 | V33: 0 | W33: 0 | X33: 0 | Y33: 0 | Z33: 0
A34: Other
A35: COGS, ths. UAN | B35: 674.79011 | C35: 3566.141 | D35: 3588.7333 | E35: 2380.7946 | F35: 2360.7434 | G35: 3424.4145 | H35: 3649.2242 | I35: 2761.3183 | J35: 917.76474 | K35: 3536.2314 | L35: 4428.7007 | M35: 2509.9372 | N35: 2146.3393 | O35: 0 | P35: 0 | Q35: 0 | R35: 0 | S35: 0 | T35: 0 | U35: 0 | V35: 0 | W35: 0 | X35: 0 | Y35: 0 | Z35: 0
A36: Total | B36: =B5+B9+B13+B17+B21+B25+B29+B33+B35 -> 89468.323 | C36: =C5+C9+C13+C17+C21+C25+C29+C33+C35 -> 168385.51 | D36: =D5+D9+D13+D17+D21+D25+D29+D33+D35 -> 211331 | E36: =E5+E9+E13+E17+E21+E25+E29+E33+E35 -> 160344.73 | F36: =F5+F9+F13+F17+F21+F25+F29+F33+F35 -> 144339.06 | G36: =G5+G9+G13+G17+G21+G25+G29+G33+G35 -> 191698.5 | H36: =H5+H9+H13+H17+H21+H25+H29+H33+H35 -> 211024.61 | I36: =I5+I9+I13+I17+I21+I25+I29+I33+I35 -> 189879.1 | ... N36: =N5+N9+N13+N17+N21+N25+N29+N33+N35 -> 159476.16 | O36: 0 | P36: 0 | Q36: 0 | R36: 0 | S36: 0 | T36: 0 | U36: 0 | V36: 0 | W36: 0 | X36: 0 | Y36: 0 | Z36: 0

Sheet Working Capital_Actual
A1: Indicator | B1: 44835 | C1: 44927 | D1: 45017 | E1: 45108 | F1: 45200 | G1: 45292 | H1: 45383 | I1: 45474 | J1: 45566 | K1: 45658 | L1: 45748 | M1: 45839 | N1: 45931 | O1: 46023 | P1: 46113 | Q1: 46204 | R1: 46296 | S1: 46388 | T1: 46478 | U1: 46569 | V1: 46661 | W1: 46753 | X1: 46844 | Y1: 46935 | Z1: 47027
A2: Total Inventory | B2: 168142.95 | C2: 176213.39 | D2: 183797.05 | E2: 188097.33 | F2: 195169.87 | G2: 205630.12 | H2: 219371.73 | I2: 213132.15 | J2: 226775.31 | K2: 238177.55 | L2: 253364.29 | M2: 245838.12 | N2: 262120.27 | O2: 0 | P2: 0 | Q2: 0 | R2: 0 | S2: 0 | T2: 0 | U2: 0 | V2: 0 | W2: 0 | X2: 0 | Y2: 0 | Z2: 0
A3: Total Trade Receivables | B3: 109164.73 | C3: 109364.8 | D3: 104862.03 | E3: 107460.71 | F3: 144869.31 | G3: 158085.87 | H3: 128120.81 | I3: 110365.99 | J3: 100237.62 | K3: 143107.01 | L3: 154871.78 | M3: 149712.57 | N3: 150175.75 | O3: 0 | P3: 0 | Q3: 0 | R3: 0 | S3: 0 | T3: 0 | U3: 0 | V3: 0 | W3: 0 | X3: 0 | Y3: 0 | Z3: 0
A4: Total Payables | B4: 54982.535 | C4: 21185.39 | D4: 49077.649 | E4: 6967.9674 | F4: 20990.428 | G4: 34687.193 | H4: 36120.436 | I4: 9803.0302 | J4: 9235 | K4: 10863.811 | L4: 12568 | M4: 11506 | N4: 14111 | O4: 0 | P4: 0 | Q4: 0 | R4: 0 | S4: 0 | T4: 0 | U4: 0 | V4: 0 | W4: 0 | X4: 0 | Y4: 0 | Z4: 0

Sheet CapEx_Actual
A1: Line Item | B1: 44835 | C1: 44927 | D1: 45017 | E1: 45108 | F1: 45200 | G1: 45292 | H1: 45383 | I1: 45474 | J1: 45566 | K1: 45658 | L1: 45748 | M1: 45839 | N1: 45931 | O1: 46023 | P1: 46113 | Q1: 46204 | R1: 46296 | S1: 46388 | T1: 46478 | U1: 46569 | V1: 46661 | W1: 46753 | X1: 46844 | Y1: 46935 | Z1: 47027 | AA1: 47119 | AB1: 47209 | AC1: 47300 | AD1: 47392
A2: Entity A NCA (Opening) | B2: 658000 | C2: 676316.88 | D2: 693311.76 | E2: 706740.84 | F2: 719109.23 | G2: 781030.87 | H2: 836012 | I2: 881245 | J2: =I3 -> 956145 | K2: =J3 -> 986147 | L2: =K3 -> 990116 | M2: =L3 -> 997360 | N2: =M3 -> 1002483 | O2: 0 | P2: 0 | Q2: 0 | R2: 0 | S2: 0 | T2: 0 | U2: 0 | V2: 0 | W2: 0 | X2: 0 | Y2: 0 | Z2: 0 | AA2: 0 | AB2: 0 | AC2: 0 | AD2: 0
A3: Entity A NCA (Closing) | B3: 676316.88 | C3: 693311.76 | D3: 706740.84 | E3: 719109.23 | F3: 781030.87 | G3: 836012 | H3: 881245 | I3: 956145 | J3: 986147 | K3: 990116 | L3: 997360 | M3: 1002483 | N3: 1005564 | O3: 0 | P3: 0 | Q3: 0 | R3: 0 | S3: 0 | T3: 0 | U3: 0 | V3: 0 | W3: 0 | X3: 0 | Y3: 0 | Z3: 0 | AA3: 0 | AB3: 0 | AC3: 0 | AD3: 0
A4: Entity B NCA (Opening) | B4: 201300 | C4: 198508.55 | D4: 195666.02 | E4: 192200.73 | F4: 188698.13 | G4: 185166.98 | H4: 181911.09 | I4: 178620.82 | J4: 175380.91 | K4: 172239.82 | L4: 169208.98 | M4: 166265.97 | N4: 163376.87 | O4: 0 | P4: 0 | Q4: 0 | R4: 0 | S4: 0 | T4: 0 | U4: 0 | V4: 0 | W4: 0 | X4: 0 | Y4: 0 | Z4: 0 | AA4: 0 | AB4: 0 | AC4: 0 | AD4: 0
A5: Entity B NCA (Closing) | B5: 198508.55 | C5: 195666.02 | D5: 192200.73 | E5: 188698.13 | F5: 185166.98 | G5: 181911.09 | H5: 178620.82 | I5: 175380.91 | J5: 172239.82 | K5: 169208.98 | L5: 166265.97 | M5: 163376.87 | N5: 160592.18 | O5: 0 | P5: 0 | Q5: 0 | R5: 0 | S5: 0 | T5: 0 | U5: 0 | V5: 0 | W5: 0 | X5: 0 | Y5: 0 | Z5: 0 | AA5: 0 | AB5: 0 | AC5: 0 | AD5: 0
A6: Depretiation | B6: 11916 | C6: 12527 | D6: 15744 | E6: 16382 | F6: 16988 | G6: 16110 | H6: 16780 | I6: 17012 | J6: 16950 | K6: 16830 | L6: 16780 | M6: 16934 | N6: 16750
A7: CapEx | B7: =B3+B5-B2-B4 -> 15525.432 | C7: =C3+C5-C2-C4 -> 14152.348 | D7: =D3+D5-D2-D4 -> 9963.7909 | E7: =E3+E5-E2-E4 -> 8865.7923 | F7: =F3+F5-F2-F4 -> 58390.495 | G7: =G3+G5-G2-G4 -> 51725.235 | H7: =H3+H5-H2-H4 -> 41942.729 | I7: =I3+I5-I2-I4 -> 71660.09 | ... AD7: =AD3+AD5-AD2-AD4 -> 0

Sheet Debt Schedule_Actual
A1: Line Item | B1: 44835 | C1: 44927 | D1: 45017 | E1: 45108 | F1: 45200 | G1: 45292 | H1: 45383 | I1: 45474 | J1: 45566 | K1: 45658 | L1: 45748 | M1: 45839 | N1: 45931 | O1: 46023 | P1: 46113 | Q1: 46204 | R1: 46296 | S1: 46388 | T1: 46478 | U1: 46569 | V1: 46661 | W1: 46753 | X1: 46844 | Y1: 46935 | Z1: 47027
A2: Opening Loan Balance | B2: 0 | C2: =B5 -> 0 | D2: =C5 -> 12000 | E2: =D5 -> 0 | F2: =E5 -> 0 | G2: =F5 -> 2000 | H2: =G5 -> 24000 | I2: =H5 -> 28000 | J2: =I5 -> 42000 | ... Z2: =Y5 -> 0
A3: Loan Drawdown | B3: 0 | C3: 12000 | D3: 0 | E3: 0 | F3: 2000 | G3: 22000 | H3: 4000 | I3: 14000 | J3: 0 | K3: 0 | L3: 0 | M3: 0 | N3: 0 | O3: 0 | P3: 0 | Q3: 0 | R3: 0 | S3: 0 | T3: 0 | U3: 0 | V3: 0 | W3: 0 | X3: 0 | Y3: 0 | Z3: 0
A4: Loan Repayment | B4: 0 | C4: 0 | D4: 12000 | E4: 0 | F4: 0 | G4: 0 | H4: 0 | I4: 0 | J4: 0 | K4: 10000 | L4: 32000 | M4: 0 | N4: 0 | O4: 0 | P4: 0 | Q4: 0 | R4: 0 | S4: 0 | T4: 0 | U4: 0 | V4: 0 | W4: 0 | X4: 0 | Y4: 0 | Z4: 0
A5: Closing Loan Balance | B5: =B2+B3-B4 -> 0 | C5: =C2+C3-C4 -> 12000 | D5: =D2+D3-D4 -> 0 | E5: =E2+E3-E4 -> 0 | F5: =F2+F3-F4 -> 2000 | G5: =G2+G3-G4 -> 24000 | H5: =H2+H3-H4 -> 28000 | I5: =I2+I3-I4 -> 42000 | ... Z5: =Z2+Z3-Z4 -> 0
A6: Interest Rate | B6: 0.19 | C6: 0.19 | D6: 0.19 | E6: 0.19 | F6: 0.19 | G6: 0.19 | H6: 0.19 | I6: 0.19 | J6: 0.19 | K6: 0.19 | L6: 0.19 | M6: 0.19 | N6: 0.19 | O6: 0.19 | P6: 0.19 | Q6: 0.19 | R6: 0.19 | S6: 0.19 | T6: 0.19 | U6: 0.19 | V6: 0.19 | W6: 0.19 | X6: 0.19 | Y6: 0.19 | Z6: 0.19
A7: Interest Expense | B7: =(B2+B5)*B6/2 -> 0 | C7: =(C2+C5)*C6/2 -> 1140 | D7: =(D2+D5)*D6/2 -> 1140 | E7: =(E2+E5)*E6/2 -> 0 | F7: =(F2+F5)*F6/2 -> 190 | G7: =(G2+G5)*G6/2 -> 2470 | H7: =(H2+H5)*H6/2 -> 4940 | I7: =(I2+I5)*I6/2 -> 6650 | ... Z7: =(Z2+Z5)*Z6/2 -> 0

Sheet DimDirection
A1: DirectionKey | B1: Direction
A2: 1 | B2: Business Line A
A3: 2 | B3: Business Line B
A4: 3 | B4: Business Line C
A5: 4 | B5: Business Line D
A6: 5 | B6: Business Line E
A7: 6 | B7: Business Line F
A8: 7 | B8: Business Line G
A9: 8 | B9: Business Line H
A10: 9 | B10: Other
A11: 10 | B11: Total

Sheet OPEX_Actual
A1: OPEX Category | B1: OPEX Subcategory | C1: 44835 | D1: 44927 | E1: 45017 | F1: 45108 | G1: 45200 | H1: 45292 | I1: 45383 | J1: 45474 | K1: 45566 | L1: 45658 | M1: 45748 | N1: 45839 | O1: 45931 | P1: 46023 | Q1: 46113 | R1: 46204 | S1: 46296 | T1: 46388 | U1: 46478 | V1: 46569 | W1: 46661 | X1: 46753 | Y1: 46844 | Z1: 46935 | AA1: 47027
A2: Administrative Expenses | B2: Salaries | C2: 1213.54 | D2: 1259.612 | E2: 1303.3384 | F2: 1354.4274 | G2: 1391.9211 | H2: 1435.1032 | I2: 1476.2019 | J2: 1533.1835 | K2: 1579.9146 | L2: 1625.4824 | M2: 1669.1086 | N2: 1719.2083 | O2: 1770.4196 | P2: 0 | Q2: =P2*(RAND()*(1.04-1.025)+1.025) -> 0 | R2: =Q2*(RAND()*(1.04-1.025)+1.025) -> 0 | S2: =R2*(RAND()*(1.04-1.025)+1.025) -> 0 | T2: =S2*(RAND()*(1.04-1.025)+1.025) -> 0 | U2: =T2*(RAND()*(1.04-1.025)+1.025) -> 0 | V2: =U2*(RAND()*(1.04-1.025)+1.025) -> 0 | W2: =V2*(RAND()*(1.04-1.025)+1.025) -> 0 | X2: =W2*(RAND()*(1.04-1.025)+1.025) -> 0 | ... AA2: =Z2*(RAND()*(1.04-1.025)+1.025) -> 0
A3: Administrative Expenses | B3: Bonuses | C3: 231.45 | D3: 261.03243 | E3: 265.49975 | F3: 284.00178 | G3: 269.90844 | H3: 269.20512 | I3: 268.87172 | J3: 261.20963 | K3: 249.076 | L3: 280.72525 | M3: 287.83389 | N3: 281.51813 | O3: 318.77545 | P3: 0 | Q3: =P3*(RAND()*(1.15-0.93)+0.93) -> 0 | R3: =Q3*(RAND()*(1.15-0.93)+0.93) -> 0 | S3: =R3*(RAND()*(1.15-0.93)+0.93) -> 0 | T3: =S3*(RAND()*(1.15-0.93)+0.93) -> 0 | U3: =T3*(RAND()*(1.15-0.93)+0.93) -> 0 | V3: =U3*(RAND()*(1.15-0.93)+0.93) -> 0 | W3: =V3*(RAND()*(1.15-0.93)+0.93) -> 0 | X3: =W3*(RAND()*(1.15-0.93)+0.93) -> 0 | ... AA3: =Z3*(RAND()*(1.15-0.93)+0.93) -> 0
A4: Administrative Expenses | B4: Utilities | C4: 3133.4 | D4: 3045.1297 | E4: 3090.5479 | F4: 3552.5214 | G4: 3831.0335 | H4: 4334.5663 | I4: 4463.8461 | J4: 4545.6563 | K4: 4853.0415 | L4: 5220.1145 | M4: 5802.2082 | N4: 6133.3318 | O4: 6888.599 | P4: 0 | Q4: =P4*(RAND()*(1.15-0.93)+0.93) -> 0 | R4: =Q4*(RAND()*(1.15-0.93)+0.93) -> 0 | S4: =R4*(RAND()*(1.15-0.93)+0.93) -> 0 | T4: =S4*(RAND()*(1.15-0.93)+0.93) -> 0 | U4: =T4*(RAND()*(1.15-0.93)+0.93) -> 0 | V4: =U4*(RAND()*(1.15-0.93)+0.93) -> 0 | W4: =V4*(RAND()*(1.15-0.93)+0.93) -> 0 | X4: =W4*(RAND()*(1.15-0.93)+0.93) -> 0 | ... AA4: =Z4*(RAND()*(1.15-0.93)+0.93) -> 0
A5: Administrative Expenses | B5: Internet & Comunication | C5: 124.6 | D5: 128.82975 | E5: 134.6744 | F5: 139.53921 | G5: 142.34561 | H5: 144.0296 | I5: 147.31622 | J5: 149.05274 | K5: 155.58363 | L5: 158.79109 | M5: 160.5522 | N5: 168.2877 | O5: 170.20831 | P5: 0 | Q5: =P5*(RAND()*(1.05-1.1)+1.05) -> 0 | R5: =Q5*(RAND()*(1.05-1.1)+1.05) -> 0 | S5: =R5*(RAND()*(1.05-1.1)+1.05) -> 0 | T5: =S5*(RAND()*(1.05-1.1)+1.05) -> 0 | U5: =T5*(RAND()*(1.05-1.1)+1.05) -> 0 | V5: =U5*(RAND()*(1.05-1.1)+1.05) -> 0 | W5: =V5*(RAND()*(1.05-1.1)+1.05) -> 0 | X5: =W5*(RAND()*(1.05-1.1)+1.05) -> 0 | ... AA5: =Z5*(RAND()*(1.05-1.1)+1.05) -> 0
A6: Administrative Expenses | B6: IT Servise | C6: 454.3 | D6: 466.74774 | E6: 479.10852 | F6: 492.53368 | G6: 515.17549 | H6: 528.77932 | I6: 544.84116 | J6: 556.04155 | K6: 571.86403 | L6: 590.23954 | M6: 617.63347 | N6: 625.76083 | O6: 649.43944 | P6: 0 | Q6: =P6*(RAND()*(1.05-1.01)+1.01) -> 0 | R6: =Q6*(RAND()*(1.05-1.01)+1.01) -> 0 | S6: =R6*(RAND()*(1.05-1.01)+1.01) -> 0 | T6: =S6*(RAND()*(1.05-1.01)+1.01) -> 0 | U6: =T6*(RAND()*(1.05-1.01)+1.01) -> 0 | V6: =U6*(RAND()*(1.05-1.01)+1.01) -> 0 | W6: =V6*(RAND()*(1.05-1.01)+1.01) -> 0 | X6: =W6*(RAND()*(1.05-1.01)+1.01) -> 0 | ... AA6: =Z6*(RAND()*(1.05-1.01)+1.01) -> 0
A7: Administrative Expenses | B7: Insurance | C7: 64.12 | D7: 64.12 | E7: 64.12 | F7: 64.12 | G7: 64.12 | H7: 64.12 | I7: 64.12 | J7: 64.12 | K7: 64.12 | L7: 64.12 | M7: 64.12 | N7: 64.12 | O7: 64.12 | P7: 0 | Q7: 0 | R7: 0 | S7: 0 | T7: 0 | U7: 0 | V7: 0 | W7: 0 | X7: 0 | Y7: 0 | Z7: 0 | AA7: 0
A8: Selling Expenses | B8: Salaries | C8: 620.4 | D8: 638.39155 | E8: 655.91464 | F8: 674.66164 | G8: 692.67777 | H8: 713.40521 | I8: 740.52879 | J8: 762.27514 | K8: 783.1938 | L8: 808.85228 | M8: 839.55499 | N8: 868.35887 | O8: 891.31609 | P8: 0 | Q8: =P8*(RAND()*(1.04-1.025)+1.025) -> 0 | R8: =Q8*(RAND()*(1.04-1.025)+1.025) -> 0 | S8: =R8*(RAND()*(1.04-1.025)+1.025) -> 0 | T8: =S8*(RAND()*(1.04-1.025)+1.025) -> 0 | U8: =T8*(RAND()*(1.04-1.025)+1.025) -> 0 | V8: =U8*(RAND()*(1.04-1.025)+1.025) -> 0 | W8: =V8*(RAND()*(1.04-1.025)+1.025) -> 0 | X8: =W8*(RAND()*(1.04-1.025)+1.025) -> 0 | ... AA8: =Z8*(RAND()*(1.04-1.025)+1.025) -> 0
A9: Selling Expenses | B9: Bonuses | C9: 406.30706 | D9: 733.6875 | E9: 965.50835 | F9: 755.10175 | G9: 648.81721 | H9: 866.55735 | I9: 957.6906 | J9: 828.30601 | K9: 608.79068 | L9: 977.54155 | M9: 1315.0039 | N9: 856.92771 | O9: 772.57752 | P9: ='Cash Flow Statement_Actual'!O3*0.003 -> 0 | Q9: ='Cash Flow Statement_Actual'!P3*0.003 -> 0 | R9: ='Cash Flow Statement_Actual'!Q3*0.003 -> 0 | S9: ='Cash Flow Statement_Actual'!R3*0.003 -> 0 | T9: ='Cash Flow Statement_Actual'!S3*0.003 -> 0 | U9: ='Cash Flow Statement_Actual'!T3*0.003 -> 0 | V9: ='Cash Flow Statement_Actual'!U3*0.003 -> 0 | W9: ='Cash Flow Statement_Actual'!V3*0.003 -> 0 | ... AA9: ='Cash Flow Statement_Actual'!Z3*0.003 -> 0
A10: Selling Expenses | B10: Advertising | C10: 248.6 | D10: 255.21262 | E10: 261.66167 | F10: 268.89322 | G10: 279.2899 | H10: 287.01607 | I10: 294.70105 | J10: 304.07208 | K10: 315.33863 | L10: 323.49893 | M10: 335.13531 | N10: 346.93768 | O10: 360.40324 | P10: 0 | Q10: =P10*(RAND()*(1.04-1.025)+1.025) -> 0 | R10: =Q10*(RAND()*(1.04-1.025)+1.025) -> 0 | S10: =R10*(RAND()*(1.04-1.025)+1.025) -> 0 | T10: =S10*(RAND()*(1.04-1.025)+1.025) -> 0 | U10: =T10*(RAND()*(1.04-1.025)+1.025) -> 0 | V10: =U10*(RAND()*(1.04-1.025)+1.025) -> 0 | W10: =V10*(RAND()*(1.04-1.025)+1.025) -> 0 | X10: =W10*(RAND()*(1.04-1.025)+1.025) -> 0 | ... AA10: =Z10*(RAND()*(1.04-1.025)+1.025) -> 0
A11: Selling Expenses | B11: Marketing | C11: 79.3 | D11: 89.794657 | E11: 94.729324 | F11: 94.498663 | G11: 96.368307 | H11: 97.423273 | I11: 108.72563 | J11: 122.09133 | K11: 133.0066 | L11: 143.68358 | M11: 135.20748 | N11: 130.22416 | O11: 135.51893 | P11: 0 | Q11: 0 | R11: 0 | S11: 0 | T11: 0 | U11: 0 | V11: 0 | W11: 0 | X11: 0 | Y11: 0 | Z11: 0 | AA11: 0
A12: Selling Expenses | B12: Transportation | C12: 9288.7606 | D12: 20248.915 | E12: 20134.943 | F12: 16969.138 | G12: 15485.439 | H12: 25411.761 | I12: 23029.012 | J12: 17590.926 | K12: 9890.0064 | L12: 27000.648 | M12: 25273.361 | N12: 18631.324 | O12: 16056.096 | P12: 0 | Q12: 0 | R12: 0 | S12: 0 | T12: 0 | U12: 0 | V12: 0 | W12: 0 | X12: 0 | Y12: 0 | Z12: 0 | AA12: 0
A13: Selling Expenses | B13: Business Trip | C13: 148.4 | D13: 152.18445 | E13: 158.11962 | F13: 163.24637 | G13: 168.87378 | H13: 173.16675 | I13: 177.90491 | J13: 182.8661 | K13: 188.75786 | L13: 194.11723 | M13: 199.18244 | N13: 206.07991 | O13: 213.12097 | P13: 0 | Q13: 0 | R13: 0 | S13: 0 | T13: 0 | U13: 0 | V13: 0 | W13: 0 | X13: 0 | Y13: 0 | Z13: 0 | AA13: 0
A14: Other Operating Expenses | B14: Environmental Cost | C14: 2156.7 | D14: 2215.1826 | E14: 1241 | F14: 2034.12 | G14: 2095.7683 | H14: 2165.4237 | I14: 2235.8768 | J14: 2323.7166 | K14: 2395.2777 | L14: 2463.0502 | M14: 2543.5205 | N14: 2614.3 | O14: 2686.7172 | P14: 0 | Q14: 0 | R14: 0 | S14: 0 | T14: 0 | U14: 0 | V14: 0 | W14: 0 | X14: 0 | Y14: 0 | Z14: 0 | AA14: 0
A15: Other Operating Expenses | B15: Write-offs | C15: 7594.8 | D15: 2736.5477 | E15: 143.87342 | F15: 101.25287 | G15: 13885.911 | H15: 32749.536 | I15: 3402.7361 | J15: 12534.727 | K15: 14584.229 | L15: 18822.371 | M15: 10284.65 | N15: 247.52386 | O15: 2927.0651 | P15: 0 | Q15: 0 | R15: 0 | S15: 0 | T15: 0 | U15: 0 | V15: 0 | W15: 0 | X15: 0 | Y15: 0 | Z15: 0 | AA15: 0
A16: Other Operating Expenses | B16: Taxes & Fees | C16: 3124.4 | D16: 3221.0004 | E16: 3310.4206 | F16: 3430.8061 | G16: 3548.9278 | H16: 3643.2448 | I16: 3749.3362 | J16: 3855.3048 | K16: 3995.3344 | L16: 4120.1875 | M16: 4269.1831 | N16: 4419.8355 | O16: 4596.4835 | P16: 0 | Q16: 0 | R16: 0 | S16: 0 | T16: 0 | U16: 0 | V16: 0 | W16: 0 | X16: 0 | Y16: 0 | Z16: 0 | AA16: 0
A17: Other Operating Expenses | B17: Health & Safety | C17: 913.1 | D17: 946.66928 | E17: 972.70599 | F17: 1008.821 | G17: 1039.3927 | H17: 1080.7955 | I17: 1108.1509 | J17: 1139.2514 | K17: 1172.4593 | L17: 1218.2915 | M17: 1251.646 | N17: 1296.3407 | O17: 1342.7342 | P17: 0 | Q17: 0 | R17: 0 | S17: 0 | T17: 0 | U17: 0 | V17: 0 | W17: 0 | X17: 0 | Y17: 0 | Z17: 0 | AA17: 0
